yaab/__init__.py
yaab/adapter.py
yaab/mixin.py
yaab-0.2.2.dist-info/AUTHORS.rst
yaab-0.2.2.dist-info/LICENSE
yaab-0.2.2.dist-info/METADATA
yaab-0.2.2.dist-info/WHEEL
yaab-0.2.2.dist-info/top_level.txt
yaab-0.2.2.dist-info/RECORD
