Metadata-Version: 2.1
Name: yaab
Version: 0.2.2
Summary: YAAB aims to provide a flexible base for Adapter Design Pattern implementations based on dataclasses.
Home-page: https://github.com/panagiks/yaab
Author: Kolokotronis Panagiotis
Author-email: panagiks@gmail.com
License: MIT license
Keywords: yaab
Platform: UNKNOWN
Classifier: Development Status :: 2 - Pre-Alpha
Classifier: Intended Audience :: Developers
Classifier: License :: OSI Approved :: MIT License
Classifier: Natural Language :: English
Classifier: Programming Language :: Python :: 3
Classifier: Programming Language :: Python :: 3.6
Classifier: Programming Language :: Python :: 3.7
Classifier: Programming Language :: Python :: 3.8
Requires-Python: >=3.6
Requires-Dist: dataclasses ; python_version < "3.7"
